pubapp/__init__.py
pubapp/logger.py
NanuTestApp-1.0.7.dist-info/METADATA
NanuTestApp-1.0.7.dist-info/WHEEL
NanuTestApp-1.0.7.dist-info/top_level.txt
NanuTestApp-1.0.7.dist-info/RECORD
