Metadata-Version: 2.1
Name: NanuTestApp
Version: 1.0.7
Summary: nanupubapp2
Home-page: https://github.com/pradeep9873/
Author: rahim
Author-email: zenith.rahim@gmail.com
License: MIT
Keywords: PubApp rest realtime pub/sub and rpc service
Classifier: License :: OSI Approved :: MIT License
Classifier: Development Status :: 4 - Beta
Classifier: Intended Audience :: Developers
Classifier: Programming Language :: Python :: 3.6
Classifier: Programming Language :: Python :: 3.7
Classifier: Programming Language :: Python :: 3.8
Classifier: Programming Language :: Python :: 3.9
Classifier: Programming Language :: Python :: 3.10
